poset/__init__.py
poset/__main__.py
poset/core/__init__.py
poset/tests/__init__.py
poset/tests/test_1984.py
poset-0.0.0.dev0.dist-info/licenses/LICENSE.txt
poset-0.0.0.dev0.dist-info/METADATA
poset-0.0.0.dev0.dist-info/WHEEL
poset-0.0.0.dev0.dist-info/top_level.txt
poset-0.0.0.dev0.dist-info/RECORD
